puya_bignumber/__init__.py
puya_bignumber/bignumber.py
puya_bignumber/common.py
puya_bignumber/py.typed
puya_bignumber-0.4.1.dist-info/LICENSE
puya_bignumber-0.4.1.dist-info/METADATA
puya_bignumber-0.4.1.dist-info/WHEEL
puya_bignumber-0.4.1.dist-info/RECORD
