Metadata-Version: 2.1
Name: puya-bignumber
Version: 0.4.1
Summary: Math Library for big numbers in Puya for Algorand
Home-page: https://github.com/Helium-Labs/Puya-BigNumber
License: GNU GPLv3
Author: Winton Nathan-Roberts
Author-email: winton.nathan.roberts@gmail.com
Requires-Python: >=3.12,<4.0
Classifier: License :: Other/Proprietary License
Classifier: Programming Language :: Python :: 3
Classifier: Programming Language :: Python :: 3.12
Requires-Dist: algorand-python (>=2.1.0,<3.0.0)
Requires-Dist: puyapy (>=3.1.0,<4.0.0)
Requires-Dist: py-algorand-sdk (>=2.6.1,<3.0.0)
Project-URL: Repository, https://github.com/Helium-Labs/Puya-BigNumber
